pandas_openscm/__init__.py
pandas_openscm/accessors/__init__.py
pandas_openscm/accessors/dataframe.py
pandas_openscm/accessors/index.py
pandas_openscm/accessors/series.py
pandas_openscm/comparison.py
pandas_openscm/db/__init__.py
pandas_openscm/db/backends.py
pandas_openscm/db/csv.py
pandas_openscm/db/deleting.py
pandas_openscm/db/feather.py
pandas_openscm/db/in_memory.py
pandas_openscm/db/interfaces.py
pandas_openscm/db/loading.py
pandas_openscm/db/netcdf.py
pandas_openscm/db/openscm_db.py
pandas_openscm/db/path_handling.py
pandas_openscm/db/reader.py
pandas_openscm/db/rewriting.py
pandas_openscm/db/saving.py
pandas_openscm/exceptions.py
pandas_openscm/grouping.py
pandas_openscm/index_manipulation.py
pandas_openscm/indexing.py
pandas_openscm/io.py
pandas_openscm/parallelisation.py
pandas_openscm/plotting.py
pandas_openscm/py.typed
pandas_openscm/reshaping.py
pandas_openscm/testing.py
pandas_openscm/typing.py
pandas_openscm/unit_conversion.py
pandas_openscm-0.9.0.dist-info/WHEEL
pandas_openscm-0.9.0.dist-info/METADATA
pandas_openscm-0.9.0.dist-info/RECORD
