Metadata-Version: 2.3
Name: pandas-openscm
Version: 0.9.0
Summary: Pandas accessors for OpenSCM-related functionality.
Author: Zebedee Nicholls
Author-email: Zebedee Nicholls <zebedee.nicholls@climate-energy-college.org>
License: 3-Clause BSD License
Classifier: Development Status :: 3 - Alpha
Classifier: Intended Audience :: Science/Research
Classifier: License :: OSI Approved :: BSD License
Classifier: Natural Language :: English
Classifier: Operating System :: OS Independent
Classifier: Programming Language :: Python
Classifier: Programming Language :: Python :: 3
Classifier: Programming Language :: Python :: 3 :: Only
Classifier: Programming Language :: Python :: 3.9
Classifier: Programming Language :: Python :: 3.10
Classifier: Programming Language :: Python :: 3.11
Classifier: Programming Language :: Python :: 3.12
Classifier: Programming Language :: Python :: 3.13
Classifier: Typing :: Typed
Requires-Dist: attrs>=24.3.0
Requires-Dist: numpy>=1.26.0 ; python_full_version < '3.13'
Requires-Dist: numpy>=2.1.0 ; python_full_version >= '3.13'
Requires-Dist: pandas>=2.2.0
Requires-Dist: filelock>=3.12.3 ; extra == 'db'
Requires-Dist: netcdf4>=1.7.2 ; extra == 'db-full'
Requires-Dist: pandas-openscm[db] ; extra == 'db-full'
Requires-Dist: pyarrow>=19.0.0 ; extra == 'db-full'
Requires-Dist: xarray>=2024.7.0 ; extra == 'db-full'
Requires-Dist: attrs==25.3.0 ; extra == 'db-full-locked'
Requires-Dist: certifi==2025.8.3 ; extra == 'db-full-locked'
Requires-Dist: cftime==1.6.4.post1 ; extra == 'db-full-locked'
Requires-Dist: filelock==3.18.0 ; extra == 'db-full-locked'
Requires-Dist: netcdf4==1.7.2 ; extra == 'db-full-locked'
Requires-Dist: numpy==2.0.2 ; python_full_version < '3.10' and extra == 'db-full-locked'
Requires-Dist: numpy==2.2.6 ; python_full_version == '3.10.*' and extra == 'db-full-locked'
Requires-Dist: numpy==2.3.2 ; python_full_version >= '3.11' and extra == 'db-full-locked'
Requires-Dist: packaging==24.2 ; extra == 'db-full-locked'
Requires-Dist: pandas==2.3.1 ; extra == 'db-full-locked'
Requires-Dist: pyarrow==21.0.0 ; extra == 'db-full-locked'
Requires-Dist: python-dateutil==2.9.0.post0 ; extra == 'db-full-locked'
Requires-Dist: pytz==2025.2 ; extra == 'db-full-locked'
Requires-Dist: six==1.17.0 ; extra == 'db-full-locked'
Requires-Dist: tzdata==2025.2 ; extra == 'db-full-locked'
Requires-Dist: xarray==2024.7.0 ; python_full_version < '3.10' and extra == 'db-full-locked'
Requires-Dist: xarray==2025.6.1 ; python_full_version == '3.10.*' and extra == 'db-full-locked'
Requires-Dist: xarray==2025.7.1 ; python_full_version >= '3.11' and extra == 'db-full-locked'
Requires-Dist: attrs==25.3.0 ; extra == 'db-locked'
Requires-Dist: filelock==3.18.0 ; extra == 'db-locked'
Requires-Dist: numpy==2.0.2 ; python_full_version < '3.10' and extra == 'db-locked'
Requires-Dist: numpy==2.2.6 ; python_full_version == '3.10.*' and extra == 'db-locked'
Requires-Dist: numpy==2.3.2 ; python_full_version >= '3.11' and extra == 'db-locked'
Requires-Dist: pandas==2.3.1 ; extra == 'db-locked'
Requires-Dist: python-dateutil==2.9.0.post0 ; extra == 'db-locked'
Requires-Dist: pytz==2025.2 ; extra == 'db-locked'
Requires-Dist: six==1.17.0 ; extra == 'db-locked'
Requires-Dist: tzdata==2025.2 ; extra == 'db-locked'
Requires-Dist: pandas-openscm[db] ; extra == 'full'
Requires-Dist: pandas-openscm[plots] ; extra == 'full'
Requires-Dist: pandas-openscm[progress] ; extra == 'full'
Requires-Dist: attrs==25.3.0 ; extra == 'full-locked'
Requires-Dist: colorama==0.4.6 ; sys_platform == 'win32' and extra == 'full-locked'
Requires-Dist: contourpy==1.3.0 ; python_full_version < '3.10' and extra == 'full-locked'
Requires-Dist: contourpy==1.3.2 ; python_full_version == '3.10.*' and extra == 'full-locked'
Requires-Dist: contourpy==1.3.3 ; python_full_version >= '3.11' and extra == 'full-locked'
Requires-Dist: cycler==0.12.1 ; extra == 'full-locked'
Requires-Dist: filelock==3.18.0 ; extra == 'full-locked'
Requires-Dist: fonttools==4.59.0 ; extra == 'full-locked'
Requires-Dist: importlib-resources==6.5.2 ; python_full_version < '3.10' and extra == 'full-locked'
Requires-Dist: kiwisolver==1.4.7 ; python_full_version < '3.10' and extra == 'full-locked'
Requires-Dist: kiwisolver==1.4.8 ; python_full_version >= '3.10' and extra == 'full-locked'
Requires-Dist: matplotlib==3.9.4 ; python_full_version < '3.10' and extra == 'full-locked'
Requires-Dist: matplotlib==3.10.5 ; python_full_version >= '3.10' and extra == 'full-locked'
Requires-Dist: numpy==2.0.2 ; python_full_version < '3.10' and extra == 'full-locked'
Requires-Dist: numpy==2.2.6 ; python_full_version == '3.10.*' and extra == 'full-locked'
Requires-Dist: numpy==2.3.2 ; python_full_version >= '3.11' and extra == 'full-locked'
Requires-Dist: packaging==24.2 ; extra == 'full-locked'
Requires-Dist: pandas==2.3.1 ; extra == 'full-locked'
Requires-Dist: pillow==11.3.0 ; extra == 'full-locked'
Requires-Dist: pyparsing==3.2.3 ; extra == 'full-locked'
Requires-Dist: python-dateutil==2.9.0.post0 ; extra == 'full-locked'
Requires-Dist: pytz==2025.2 ; extra == 'full-locked'
Requires-Dist: six==1.17.0 ; extra == 'full-locked'
Requires-Dist: tqdm==4.67.1 ; extra == 'full-locked'
Requires-Dist: tzdata==2025.2 ; extra == 'full-locked'
Requires-Dist: zipp==3.23.0 ; python_full_version < '3.10' and extra == 'full-locked'
Requires-Dist: attrs==25.3.0 ; extra == 'locked'
Requires-Dist: numpy==2.0.2 ; python_full_version < '3.10' and extra == 'locked'
Requires-Dist: numpy==2.2.6 ; python_full_version == '3.10.*' and extra == 'locked'
Requires-Dist: numpy==2.3.2 ; python_full_version >= '3.11' and extra == 'locked'
Requires-Dist: pandas==2.3.1 ; extra == 'locked'
Requires-Dist: python-dateutil==2.9.0.post0 ; extra == 'locked'
Requires-Dist: pytz==2025.2 ; extra == 'locked'
Requires-Dist: six==1.17.0 ; extra == 'locked'
Requires-Dist: tzdata==2025.2 ; extra == 'locked'
Requires-Dist: matplotlib>=3.7.1 ; extra == 'plots'
Requires-Dist: attrs==25.3.0 ; extra == 'plots-locked'
Requires-Dist: contourpy==1.3.0 ; python_full_version < '3.10' and extra == 'plots-locked'
Requires-Dist: contourpy==1.3.2 ; python_full_version == '3.10.*' and extra == 'plots-locked'
Requires-Dist: contourpy==1.3.3 ; python_full_version >= '3.11' and extra == 'plots-locked'
Requires-Dist: cycler==0.12.1 ; extra == 'plots-locked'
Requires-Dist: fonttools==4.59.0 ; extra == 'plots-locked'
Requires-Dist: importlib-resources==6.5.2 ; python_full_version < '3.10' and extra == 'plots-locked'
Requires-Dist: kiwisolver==1.4.7 ; python_full_version < '3.10' and extra == 'plots-locked'
Requires-Dist: kiwisolver==1.4.8 ; python_full_version >= '3.10' and extra == 'plots-locked'
Requires-Dist: matplotlib==3.9.4 ; python_full_version < '3.10' and extra == 'plots-locked'
Requires-Dist: matplotlib==3.10.5 ; python_full_version >= '3.10' and extra == 'plots-locked'
Requires-Dist: numpy==2.0.2 ; python_full_version < '3.10' and extra == 'plots-locked'
Requires-Dist: numpy==2.2.6 ; python_full_version == '3.10.*' and extra == 'plots-locked'
Requires-Dist: numpy==2.3.2 ; python_full_version >= '3.11' and extra == 'plots-locked'
Requires-Dist: packaging==24.2 ; extra == 'plots-locked'
Requires-Dist: pandas==2.3.1 ; extra == 'plots-locked'
Requires-Dist: pillow==11.3.0 ; extra == 'plots-locked'
Requires-Dist: pyparsing==3.2.3 ; extra == 'plots-locked'
Requires-Dist: python-dateutil==2.9.0.post0 ; extra == 'plots-locked'
Requires-Dist: pytz==2025.2 ; extra == 'plots-locked'
Requires-Dist: six==1.17.0 ; extra == 'plots-locked'
Requires-Dist: tzdata==2025.2 ; extra == 'plots-locked'
Requires-Dist: zipp==3.23.0 ; python_full_version < '3.10' and extra == 'plots-locked'
Requires-Dist: tqdm>=4.0.0 ; extra == 'progress'
Requires-Dist: attrs==25.3.0 ; extra == 'progress-locked'
Requires-Dist: colorama==0.4.6 ; sys_platform == 'win32' and extra == 'progress-locked'
Requires-Dist: numpy==2.0.2 ; python_full_version < '3.10' and extra == 'progress-locked'
Requires-Dist: numpy==2.2.6 ; python_full_version == '3.10.*' and extra == 'progress-locked'
Requires-Dist: numpy==2.3.2 ; python_full_version >= '3.11' and extra == 'progress-locked'
Requires-Dist: pandas==2.3.1 ; extra == 'progress-locked'
Requires-Dist: python-dateutil==2.9.0.post0 ; extra == 'progress-locked'
Requires-Dist: pytz==2025.2 ; extra == 'progress-locked'
Requires-Dist: six==1.17.0 ; extra == 'progress-locked'
Requires-Dist: tqdm==4.67.1 ; extra == 'progress-locked'
Requires-Dist: tzdata==2025.2 ; extra == 'progress-locked'
Requires-Python: >=3.9
Project-URL: Changelog, https://pandas-openscm.readthedocs.io/en/stable/changelog
Project-URL: Documentation, https://pandas-openscm.readthedocs.io
Project-URL: Homepage, https://pandas-openscm.readthedocs.io
Project-URL: Issues, https://github.com/openscm/pandas-openscm/issues
Project-URL: Repository, https://github.com/openscm/pandas-openscm
Provides-Extra: db
Provides-Extra: db-full
Provides-Extra: db-full-locked
Provides-Extra: db-locked
Provides-Extra: full
Provides-Extra: full-locked
Provides-Extra: locked
Provides-Extra: plots
Provides-Extra: plots-locked
Provides-Extra: progress
Provides-Extra: progress-locked
